cae/__init__.py
cae/admin.py
cae/apps.py
cae/models.py
cae/migrations/0001_initial.py
cae/migrations/__init__.py
cae/static/css/cae.css
cae/static/js/cae.js
cae/templates/cae/base.html
cae/test_utils/__init__.py
cae/test_utils/test_app/__init__.py
cae/test_utils/test_app/admin.py
cae/test_utils/test_app/apps.py
cae/test_utils/test_app/models.py
cae/test_utils/test_app/migrations/__init__.py
django_cae-0.1.0.dist-info/AUTHORS.rst
django_cae-0.1.0.dist-info/LICENSE
django_cae-0.1.0.dist-info/METADATA
django_cae-0.1.0.dist-info/WHEEL
django_cae-0.1.0.dist-info/top_level.txt
django_cae-0.1.0.dist-info/RECORD
