Metadata-Version: 2.1
Name: django-cae
Version: 0.1.0
Summary: Classificação Portuguesa das Actividades Económicas
Home-page: https://github.com/adevolutio/django-cae
Author: Evolutio
Author-email: jpolonia@evolutio.pt
License: MIT
Keywords: django-cae
Platform: UNKNOWN
Classifier: Development Status :: 3 - Alpha
Classifier: Framework :: Django :: 2.1
Classifier: Intended Audience :: Developers
Classifier: License :: OSI Approved :: BSD License
Classifier: Natural Language :: English
Classifier: Programming Language :: Python :: 2
Classifier: Programming Language :: Python :: 2.7
Classifier: Programming Language :: Python :: 3
Classifier: Programming Language :: Python :: 3.5
Classifier: Programming Language :: Python :: 3.6
Requires-Dist: django-model-utils (>=2.0)
